setup.cfg
setup.py
seaborn/__init__.py
seaborn/time_profile.py
seaborn_time_profile.egg-info/PKG-INFO
seaborn_time_profile.egg-info/SOURCES.txt
seaborn_time_profile.egg-info/dependency_links.txt
seaborn_time_profile.egg-info/entry_points.txt
seaborn_time_profile.egg-info/top_level.txt
test/test_time_profile.py