Metadata-Version: 1.1
Name: seaborn-time-profile
Version: 0.0.1
Summary: SeabornTimingProfile collects, records, and reports timingdata on code implementing a number of different executionstrategies"
Home-page: https://github.com/SeabornGames/TimingProfile
Author: Ben Christenson
Author-email: Python@BenChristenson.com
License: MIT License
Platform: UNKNOWN
Classifier: Intended Audience :: Developers
Classifier: Natural Language :: English
Classifier: License :: Other/Proprietary License
Classifier: Operating System :: POSIX :: Linux
Classifier: Programming Language :: Python
Classifier: Programming Language :: Python :: 2.7
Classifier: Programming Language :: Python :: 3.5
